.gitignore
Readme.md
setup.py
augmend/__init__.py
augmend/augmend.py
augmend/torch_utils.py
augmend/utils.py
augmend/version.py
augmend.egg-info/PKG-INFO
augmend.egg-info/SOURCES.txt
augmend.egg-info/dependency_links.txt
augmend.egg-info/top_level.txt
augmend/transforms/__init__.py
augmend/transforms/affine.py
augmend/transforms/base.py
augmend/transforms/crop.py
augmend/transforms/elastic.py
augmend/transforms/intensity.py
augmend/transforms/other.py
augmend/transforms/kernels/elastic.cl
imgs/augmerino.png
imgs/example2d.png
imgs/example3d.png
imgs/examples.png
tests/bench_elastic.py
tests/create_examples_readme.py
tests/plot_augmend.py
tests/plot_transforms.py
tests/test_augmend.py
tests/test_coupling.py
tests/test_crop.py
tests/test_elastic.py
tests/test_elastic_workers.py
tests/test_example.py
tests/test_flat_sub_array.py
tests/test_keras_multiprocessing.py
tests/test_multithread.py
tests/test_rotation.py
tests/test_tf_data.py
tests/test_torch_data.py
tests/test_transforms.py
tests/test_utils.py
tests/utils.py