Metadata-Version: 2.1
Name: augmend
Version: 0.1.2
Summary: Augmend
Home-page: https://github.com/stardist/augmend/
Author: Martin Weigert, Uwe Schmidt
License: BSD 3-Clause License
Platform: UNKNOWN
Requires-Python: >=3.5
